{
  "checkedAt": "2026-06-23T00:17:43.099Z",
  "vendors": {
    "instructure": "operational",
    "blackbaud": "operational",
    "vivi": "operational",
    "flint": "operational",
    "respondus": "operational",
    "aspiredu": "operational",
    "kahoot": "operational",
    "deltamath": "operational",
    "cloudflare": "degraded",
    "copyleaks": "operational",
    "aws": "operational",
    "explorelearning": "unknown",
    "ixl": "operational",
    "quizizz": "breakage",
    "gimkit": "operational",
    "soundtrap": "unknown",
    "noredink": "operational",
    "finalsite": "operational",
    "arbitersports": "operational",
    "rj-website": "operational",
    "myrj": "operational"
  }
}
