{
  "checkedAt": "2026-07-18T22:22:19.743Z",
  "vendors": {
    "instructure": "operational",
    "blackbaud": "degraded",
    "vivi": "operational",
    "flint": "operational",
    "respondus": "operational",
    "aspiredu": "operational",
    "kahoot": "operational",
    "deltamath": "operational",
    "cloudflare": "degraded",
    "copyleaks": "operational",
    "aws": "operational",
    "explorelearning": "unknown",
    "ixl": "unknown",
    "quizizz": "unknown",
    "gimkit": "operational",
    "soundtrap": "unknown",
    "noredink": "operational"
  }
}
